prosody_say/__init__.py
prosody_say/cli.py
prosody_say/core.py
prosody_say-0.1.4.dist-info/LICENSE
prosody_say-0.1.4.dist-info/METADATA
prosody_say-0.1.4.dist-info/WHEEL
prosody_say-0.1.4.dist-info/entry_points.txt
prosody_say-0.1.4.dist-info/top_level.txt
prosody_say-0.1.4.dist-info/RECORD
