Metadata-Version: 2.2
Name: prosody_say
Version: 0.1.4
Summary: A prosody processing library for TTS synthesis.
Home-page: https://github.com/lucafaraldi/prosody_say
Author: Luca Faraldi
Author-email: lucafaraldi@gmail.com
License: GPL-3.0
Classifier: Programming Language :: Python :: 3
Classifier: License :: OSI Approved :: GNU General Public License v3 (GPLv3)
Classifier: Operating System :: MacOS
Requires-Python: <3.13
License-File: LICENSE
Requires-Dist: nltk
Requires-Dist: numpy
Requires-Dist: spacy
Dynamic: author
Dynamic: author-email
Dynamic: classifier
Dynamic: description
Dynamic: description-content-type
Dynamic: home-page
Dynamic: license
Dynamic: requires-dist
Dynamic: requires-python
Dynamic: summary
